shannot/__init__.py
shannot/__main__.py
shannot/_protocols.py
shannot/approve.py
shannot/audit.py
shannot/checkpoint.py
shannot/cli.py
shannot/config.py
shannot/deploy.py
shannot/execute.py
shannot/interact.py
shannot/mcp_main.py
shannot/menu.py
shannot/mix_accept_input.py
shannot/mix_dump_output.py
shannot/mix_grab_output.py
shannot/mix_pypy.py
shannot/mix_remote.py
shannot/mix_socket.py
shannot/mix_subprocess.py
shannot/mix_vfs.py
shannot/pending_deletion.py
shannot/pending_write.py
shannot/py.typed
shannot/queue.py
shannot/remote.py
shannot/run_session.py
shannot/runtime.py
shannot/sandboxio.py
shannot/selftest.py
shannot/session.py
shannot/ssh.py
shannot/structs.py
shannot/vfs_procfs.py
shannot/virtualizedproc.py
shannot/mcp/__init__.py
shannot/mcp/protocol.py
shannot/mcp/server.py
shannot/mcp/server_impl.py
shannot/mcp/types.py
shannot/stubs/__init__.py
shannot/stubs/_bootlocale.py
shannot/stubs/_signal.py
shannot/stubs/pwd.py
shannot/stubs/subprocess.py
shannot-0.11.0.dist-info/licenses/LICENSE
shannot-0.11.0.dist-info/licenses/NOTICE
shannot-0.11.0.dist-info/METADATA
shannot-0.11.0.dist-info/WHEEL
shannot-0.11.0.dist-info/entry_points.txt
shannot-0.11.0.dist-info/top_level.txt
shannot-0.11.0.dist-info/RECORD
