Metadata-Version: 2.4
Name: shannot
Version: 0.11.0
Summary: Sandboxed system administration for LLM agents
Author-email: corv89 <corv89@users.noreply.github.com>
License: Apache-2.0
Project-URL: Homepage, https://github.com/corv89/shannot
Project-URL: Repository, https://github.com/corv89/shannot
Project-URL: Bug Tracker, https://github.com/corv89/shannot/issues
Project-URL: Documentation, https://corv89.github.io/shannot/
Keywords: sandbox,pypy,security,llm,diagnostics,system-administration
Classifier: Development Status :: 4 - Beta
Classifier: Intended Audience :: System Administrators
Classifier: Topic :: Security
Classifier: Topic :: System :: Systems Administration
Classifier: Programming Language :: Python :: 3
Classifier: Programming Language :: Python :: 3.11
Classifier: Programming Language :: Python :: 3.12
Classifier: Programming Language :: Python :: 3.13
Classifier: Operating System :: POSIX :: Linux
Classifier: Operating System :: MacOS
Classifier: Environment :: Console
Classifier: Typing :: Typed
Requires-Python: >=3.11
License-File: LICENSE
License-File: NOTICE
Provides-Extra: dev
Requires-Dist: pytest>=7.0; extra == "dev"
Requires-Dist: pytest-cov>=4.0; extra == "dev"
Requires-Dist: pre-commit>=3.6.0; extra == "dev"
Requires-Dist: ruff>=0.1.0; extra == "dev"
Requires-Dist: basedpyright>=1.0; extra == "dev"
Requires-Dist: mkdocs>=1.5.0; extra == "dev"
Requires-Dist: mkdocs-material>=9.0.0; extra == "dev"
Requires-Dist: mkdocstrings[python]>=0.24.0; extra == "dev"
Provides-Extra: mcp-testing
Requires-Dist: pytest>=7.0; extra == "mcp-testing"
Dynamic: license-file
